PLIS/lab5/slave/src/slave.v
module slave(
    input clk,
    input sclk,
    input mosi,
    input ss,
    output reg [3:0] led_output
);
localparam DATA_SIZE = 4;
reg [DATA_SIZE-1:0] data;
reg [1:0] bit_counter;

initial begin
    bit_counter <= 0;
    data <= 'b1111;
end

always @(posedge clk) begin
    if (ss == 0 && sclk == 0) begin
        data[bit_counter] <= mosi;
        if (bit_counter == DATA_SIZE - 1) begin
            bit_counter <= 0;
        end
        else begin
            bit_counter <= bit_counter + 1'b1;
        end
    end
    
    led_output <= data;
end

endmodule

PLIS/lab5/slave/src/slave_tb.v
`timescale 1ns / 1ns

module slave_tb();

reg clk;
reg sclk;
reg mosi;
reg ss;
wire [3:0] led_output;


slave r(
    .clk(clk), 
    .sclk(sclk), 
    .mosi(mosi),
    .ss(ss),
    .led_output(led_output)
);

initial
begin
	clk = 'b0;
    sclk = 'b1;
    ss = 'b1;
    mosi = 'b0;
    
    #100 ss = 'b0;
    
    #10 sclk = 'b0;
    #0 mosi = 'b0;
    #10 sclk = 'b1;

    #10 sclk = 'b0;
    #0 mosi = 'b0;
    #10 sclk = 'b1;

    #10 sclk = 'b0;
    #0 mosi = 'b0;
    #10 sclk = 'b1;

    #10 sclk = 'b0;
    #0 mosi = 'b1;
    #10 sclk = 'b1;
end

initial forever #(5) clk = !clk;

initial #1000 $finish;

initial
begin
  $dumpfile("./slave_out.vcd");
  $dumpvars(0, slave_tb);
end

endmodule

PLIS/lab5/slave/slave_out.vcd
$date
	Sat Dec 14 20:05:02 2024
$end
$version
	Icarus Verilog
$end
$timescale
	1ns
$end
$scope module slave_tb $end
$var wire 4 ! led_output [3:0] $end
$var reg 1 " clk $end
$var reg 1 # mosi $end
$var reg 1 $ sclk $end
$var reg 1 % ss $end
$scope module r $end
$var wire 1 " clk $end
$var wire 1 # mosi $end
$var wire 1 $ sclk $end
$var wire 1 % ss $end
$var parameter 32 & DATA_SIZE $end
$var reg 2 ' bit_counter [1:0] $end
$var reg 4 ( data [3:0] $end
$var reg 4 ) led_output [3:0] $end
$upscope $end
$upscope $end
$enddefinitions $end
$comment Show the parameter values. $end
$dumpall
b100 &
$end
#0
$dumpvars
bx )
b1111 (
b0 '
1%
1$
0#
0"
bx !
$end
#5
b1111 !
b1111 )
1"
#10
0"
#15
1"
#20
0"
#25
1"
#30
0"
#35
1"
#40
0"
#45
1"
#50
0"
#55
1"
#60
0"
#65
1"
#70
0"
#75
1"
#80
0"
#85
1"
#90
0"
#95
1"
#100
0"
0%
#105
1"
#110
0"
0$
#115
b1 '
b1110 (
1"
#120
0"
1$
#125
b1110 !
b1110 )
1"
#130
0"
0$
#135
b10 '
b1100 (
1"
#140
0"
1$
#145
b1100 !
b1100 )
1"
#150
0"
0$
#155
b11 '
b1000 (
1"
#160
0"
1$
#165
b1000 !
b1000 )
1"
#170
1#
0"
0$
#175
b0 '
1"
